tacobi/__init__.py
tacobi/bi_app.py
tacobi/data_model/__init__.py
tacobi/data_model/models.py
tacobi/data_source/__init__.py
tacobi/data_source/models.py
tacobi/data_source/cache/__init__.py
tacobi/data_source/cache/base.py
tacobi/data_source/cache/sqlite.py
tacobi/data_source/encode/__init__.py
tacobi/data_source/encode/base.py
tacobi/data_source/encode/polars.py
tacobi/data_source/encode/pydantic.py
tacobi/view/__init__.py
tacobi/view/type_utils.py
tacobi/view/view_manager.py
tacobi/view/view_models/__init__.py
tacobi/view/view_models/base.py
tacobi/view/view_models/endpoint_model.py
tacobi/view/view_models/materialized.py
tacobi/view/view_models/view.py
tacobi-0.2.2.dist-info/METADATA
tacobi-0.2.2.dist-info/WHEEL
tacobi-0.2.2.dist-info/top_level.txt
tacobi-0.2.2.dist-info/RECORD
