Metadata-Version: 2.4
Name: tacobi
Version: 0.2.2
Summary: A framework for building and running BI applications.
Requires-Python: >=3.11
Requires-Dist: apscheduler>=3.11.0
Requires-Dist: diskcache>=5.6.3
Requires-Dist: fastapi>=0.115.12
Requires-Dist: pandas>=2.2.3
Requires-Dist: pandera[polars]>=0.23.1
Requires-Dist: polars>=1.29.0
Requires-Dist: pyarrow>=20.0.0
Requires-Dist: pydantic>=2.11.4
Requires-Dist: pytest-asyncio>=0.26.0
Requires-Dist: requests>=2.32.3
Requires-Dist: rustworkx>=0.16.0
Requires-Dist: uvicorn>=0.34.2
